{
	"name": "Snowflakeestimatedsum",
	"properties": {
		"linkedServiceName": {
			"referenceName": "Snowflakejira",
			"type": "LinkedServiceReference"
		},
		"annotations": [],
		"type": "SnowflakeTable",
		"schema": [
			{
				"name": "CONTENTS",
				"type": "VARCHAR",
				"precision": 0,
				"scale": 0
			},
			{
				"name": "SPRINT_ID",
				"type": "VARCHAR",
				"precision": 0,
				"scale": 0
			},
			{
				"name": "TEXT",
				"type": "VARCHAR",
				"precision": 0,
				"scale": 0
			},
			{
				"name": "VALUE",
				"type": "VARCHAR",
				"precision": 0,
				"scale": 0
			}
		],
		"typeProperties": {
			"schema": "SNOWFLAKE",
			"table": "ESTIMATED_SUM"
		}
	},
	"type": "Microsoft.DataFactory/factories/datasets"
}